{
  "post_id": "2026-05-14-skylights-need-extra-attention-debris-can-build-up-causing-f",
  "client": "french-roofing",
  "pillar": "educational",
  "photo": "../../photos/skylights need extra attention - debris can build up causing flashing to erode faster.jpeg",
  "rendered": true,
  "notes": "Auto-generated by scripts/evergreen-generate.ts. Each platform reviewed independently in Metricool.",
  "platforms": {
    "instagram": {
      "status": "scheduled",
      "scheduled_for": "2026-05-19T17:00:00.000Z",
      "timezone": "America/Los_Angeles",
      "published_id": null
    },
    "facebook": {
      "status": "scheduled",
      "scheduled_for": "2026-05-19T17:00:00.000Z",
      "timezone": "America/Los_Angeles",
      "published_id": null
    },
    "linkedin": {
      "status": "scheduled",
      "scheduled_for": "2026-05-19T17:00:00.000Z",
      "timezone": "America/Los_Angeles",
      "published_id": null
    },
    "gmb": {
      "status": "scheduled",
      "scheduled_for": "2026-05-19T17:00:00.000Z",
      "timezone": "America/Los_Angeles",
      "published_id": null
    }
  }
}
